{"cameraMode":{"drawMode":0,"name":"Shaded","section":"Shading Mode"},"sceneLighting":true,"audioPlay":false,"sceneViewState":{"m_AlwaysRefresh":false,"showFog":true,"showSkybox":true,"showFlares":true,"showImageEffects":true,"showParticleSystems":true,"showVisualEffectGraphs":true,"m_FxEnabled":true},"in2DMode":false,"pivot":{"x":26.105052947998048,"y":-25.300643920898439,"z":109.932373046875},"rotation":{"x":-0.3289722204208374,"y":-0.17276571691036225,"z":0.06116765737533569,"w":-0.9266272783279419},"size":274.0667419433594,"orthographic":false}